{
  "generated_at": "2026-04-15T23:09:22+00:00",
  "date": "2026-04-15",
  "run_started_at": "2026-04-15T23:03:06+00:00",
  "account": "ai.tech.moments",
  "profile_url": "https://www.instagram.com/ai.tech.moments/",
  "avatar_path": "../avatars/ai.tech.moments.jpg",
  "profile_pic_url": "https://instagram.fsyq6-1.fna.fbcdn.net/v/t51.82787-19/641773918_17983292627954279_7172782271756187774_n.jpg?efg=eyJ2ZW5jb2RlX3RhZyI6InByb2ZpbGVfcGljLmRqYW5nby4xMDgwLmMxIn0&_nc_ht=instagram.fsyq6-1.fna.fbcdn.net&_nc_cat=111&_nc_oc=Q6cZ2gEEk__xpzYbh7zREQWLyYqAjVfHKNMHJIcLxq7yLkidiSiC8LV41yiGea4caJNiN6M&_nc_ohc=1OlCstWScP4Q7kNvwHCO5Eq&_nc_gid=0YKEs-QOZeVbh9ICAqiyhg&edm=AEF8tYYBAAAA&ccb=7-5&ig_cache_key=GF6xQCZnKvuYteM-AH44Px9514pjbmNDAQAB0j-ccb7-5&oh=00_Af088F_W8PlYXiZCukXRnteato1j-efH5WEuGcxAwALUXA&oe=69E5EB84&_nc_sid=1e20d2",
  "full_name": "Ai Tech Moments",
  "biography": "your daily dose of ai and technology.",
  "external_url": "",
  "is_verified": false,
  "followers": 117066,
  "following": 13,
  "posts": 48,
  "recent_post_count": 24,
  "video_post_count": 24,
  "video_posts_with_view_data": 0,
  "video_posts_with_view_data_recent_window": 0,
  "reel_view_enriched_posts": 0,
  "recent_posts_window_days": 14,
  "recent_posts_collection_window_days": 30,
  "recent_posts_target_limit": 24,
  "recent_posts_hard_limit": 240,
  "recent_posts_collection_stop_reason": "window_reached",
  "recent_posts_window_covered": true,
  "recent_posts_collection_window_covered": true,
  "oldest_recent_post_date": "2024-05-14",
  "avg_likes": 5673.58,
  "avg_comments": 40.08,
  "avg_video_views": 0,
  "avg_video_views_per_video": 0,
  "avg_video_views_per_post": 0.0,
  "total_likes_recent_window": 0,
  "total_video_views_recent_window": 0,
  "engagement_rate": 4.8807,
  "recent_posts": [
    {
      "shortcode": "DLNJ-_miyHO",
      "date": "2025-06-22",
      "likes": 385,
      "comments": 0,
      "is_video": true,
      "video_views": 0,
      "caption": "#reels #viral #trending #instagood #instagram #facebook #motivation #engineering",
      "url": "https://www.instagram.com/p/DLNJ-_miyHO/"
    },
    {
      "shortcode": "DKF3np9zNku",
      "date": "2025-05-25",
      "likes": 8284,
      "comments": 5,
      "is_video": true,
      "video_views": 0,
      "caption": "\ud83d\udc46For more.. .\ud83d\udc46\ud83e\udd73\ud83d\udc4d\ud83d\udd25\n#mechanic #job #mechaniclife #mechanical #mechanicproblems #solve #problem #ideas #newtech #newtechnology #thebest #satisfyingvideo #nextlevel #techworld #sosatis",
      "url": "https://www.instagram.com/p/DKF3np9zNku/"
    },
    {
      "shortcode": "DF5tpjBTstd",
      "date": "2025-02-10",
      "likes": 35186,
      "comments": 135,
      "is_video": true,
      "video_views": 0,
      "caption": "\ud83d\udc46For more.. .\ud83d\udc46\n#mechanic #job #mechaniclife #mechanical #mechanicproblems #solve #problem #ideas #newtech #newtechnology #thebest #satisfyingvideo #nextlevel #techworld #sosatisfyi",
      "url": "https://www.instagram.com/p/DF5tpjBTstd/"
    },
    {
      "shortcode": "DFZ4XVozQtM",
      "date": "2025-01-29",
      "likes": 1094,
      "comments": 0,
      "is_video": true,
      "video_views": 0,
      "caption": "\ud83d\udc46For more.. .\ud83d\udc46\n#mechanic #job #mechaniclife #mechanical #mechanicproblems #solve #problem #ideas #newtech #newtechnology #thebest #satisfyingvideo #nextlevel #techworld #sosatisfyi",
      "url": "https://www.instagram.com/p/DFZ4XVozQtM/"
    },
    {
      "shortcode": "DE5NZdZTlP1",
      "date": "2025-01-16",
      "likes": 717,
      "comments": 0,
      "is_video": true,
      "video_views": 0,
      "caption": "Follow for more!\ud83d\udcaf\ud83d\udc4d\n.\n.\n.\n.\n\ud83d\udcfd\ufe0f Video : (unknown) DM for Credit\n\n\ud83d\udc97 Double Tap If You Like This\n\n\ud83d\ude80 Tag Your Friends\n\n\u2764\ufe0f For Us For More Interesting Stuff Like This\n\n\ud83d\udce9 DM for credit or",
      "url": "https://www.instagram.com/p/DE5NZdZTlP1/"
    },
    {
      "shortcode": "DExRZodz-Wo",
      "date": "2025-01-13",
      "likes": 1042,
      "comments": 0,
      "is_video": true,
      "video_views": 0,
      "caption": "good idea\ud83d\udca1\n.\n.\n.\n.\n\ud83d\udcfd\ufe0f Video : (unknown) DM for Credit\n\n\ud83d\udc97 Double Tap If You Like This\n\n\ud83d\ude80 Tag Your Friends\n\n\u2764\ufe0f For Us For More Interesting Stuff Like This\n\n\ud83d\udce9 DM for credit or removal",
      "url": "https://www.instagram.com/p/DExRZodz-Wo/"
    },
    {
      "shortcode": "DD2nPcbzyMv",
      "date": "2024-12-21",
      "likes": 655,
      "comments": 0,
      "is_video": true,
      "video_views": 0,
      "caption": "good idea\ud83d\udca1\n.\n.\n.\n.\n\ud83d\udcfd\ufe0f Video : (unknown) DM for Credit\n\n\ud83d\udc97 Double Tap If You Like This\n\n\ud83d\ude80 Tag Your Friends\n\n\u2764\ufe0f For Us For More Interesting Stuff Like This\n\n\ud83d\udce9 DM for credit or removal",
      "url": "https://www.instagram.com/p/DD2nPcbzyMv/"
    },
    {
      "shortcode": "DDoiEvzui3y",
      "date": "2024-12-16",
      "likes": 568,
      "comments": 0,
      "is_video": true,
      "video_views": 0,
      "caption": "good idea\ud83d\udca1\n.\n.\n.\n.\n\ud83d\udcfd\ufe0f Video : (unknown) DM for Credit\n\n\ud83d\udc97 Double Tap If You Like This\n\n\ud83d\ude80 Tag Your Friends\n\n\u2764\ufe0f For Us For More Interesting Stuff Like This\n\n\ud83d\udce9 DM for credit or removal",
      "url": "https://www.instagram.com/p/DDoiEvzui3y/"
    },
    {
      "shortcode": "DDmY0IRu7m_",
      "date": "2024-12-15",
      "likes": 893,
      "comments": 0,
      "is_video": true,
      "video_views": 0,
      "caption": "good idea\ud83d\udca1\n.\n.\n.\n.\n\ud83d\udcfd\ufe0f Video : (unknown) DM for Credit\n\n\ud83d\udc97 Double Tap If You Like This\n\n\ud83d\ude80 Tag Your Friends\n\n\u2764\ufe0f For Us For More Interesting Stuff Like This\n\n\ud83d\udce9 DM for credit or removal",
      "url": "https://www.instagram.com/p/DDmY0IRu7m_/"
    },
    {
      "shortcode": "DBncaVtsxKB",
      "date": "2024-10-27",
      "likes": 6964,
      "comments": 30,
      "is_video": true,
      "video_views": 0,
      "caption": "Omg \ud83d\ude32 \n\n\u00a9 DM for credit or removels\n\n#viral #explore #innovation #satisfying #technology #cooltech #reels #creative #solutions #idea",
      "url": "https://www.instagram.com/p/DBncaVtsxKB/"
    },
    {
      "shortcode": "DBaxUg9pr9h",
      "date": "2024-10-22",
      "likes": 38252,
      "comments": 657,
      "is_video": true,
      "video_views": 0,
      "caption": "",
      "url": "https://www.instagram.com/p/DBaxUg9pr9h/"
    },
    {
      "shortcode": "DA5gevXscmI",
      "date": "2024-10-09",
      "likes": 4394,
      "comments": 0,
      "is_video": true,
      "video_views": 0,
      "caption": "good idea\ud83d\udca1\n.\n.\n.\n.\n\ud83d\udcfd\ufe0f Video : (unknown) DM for Credit\n\n\ud83d\udc97 Double Tap If You Like This\n\n\ud83d\ude80 Tag Your Friends\n\n\u2764\ufe0f For Us For More Interesting Stuff Like This\n\n\ud83d\udce9 DM for credit or removal",
      "url": "https://www.instagram.com/p/DA5gevXscmI/"
    },
    {
      "shortcode": "DA5gdLYtBtz",
      "date": "2024-10-09",
      "likes": 477,
      "comments": 1,
      "is_video": true,
      "video_views": 0,
      "caption": "good idea\ud83d\udca1\n.\n.\n.\n.\n\ud83d\udcfd\ufe0f Video : (unknown) DM for Credit\n\n\ud83d\udc97 Double Tap If You Like This\n\n\ud83d\ude80 Tag Your Friends\n\n\u2764\ufe0f For Us For More Interesting Stuff Like This\n\n\ud83d\udce9 DM for credit or removal",
      "url": "https://www.instagram.com/p/DA5gdLYtBtz/"
    },
    {
      "shortcode": "DAjTFIDOxMW",
      "date": "2024-09-30",
      "likes": 1206,
      "comments": 0,
      "is_video": true,
      "video_views": 0,
      "caption": "good idea\ud83d\udca1\n.\n.\n.\n.\n\ud83d\udcfd\ufe0f Video : (unknown) DM for Credit\n\n\ud83d\udc97 Double Tap If You Like This\n\n\ud83d\ude80 Tag Your Friends\n\n\u2764\ufe0f For Us For More Interesting Stuff Like This\n\n\ud83d\udce9 DM for credit or removal",
      "url": "https://www.instagram.com/p/DAjTFIDOxMW/"
    },
    {
      "shortcode": "C_mwOfrOWxJ",
      "date": "2024-09-07",
      "likes": 71,
      "comments": 1,
      "is_video": true,
      "video_views": 0,
      "caption": "\ud83d\udecd\ufe0fLINK ORDER IN BIO @iamk24__\n\ud83d\uded1SHOP NOW\ud83d\udc47 \n\ud83d\udecd\ufe0fYou can buy this products, just go to the link in the bio \n\u2705Link in Bio @iamk24__\n\ud83c\udf0eFree shipping worldwide & (Only 24 hours)\n#industry #",
      "url": "https://www.instagram.com/p/C_mwOfrOWxJ/"
    },
    {
      "shortcode": "C_Fhq8ZxmNm",
      "date": "2024-08-25",
      "likes": 694,
      "comments": 5,
      "is_video": true,
      "video_views": 0,
      "caption": "\ud83d\udecd\ufe0fLINK ORDER IN BIO @iamk24__\n\ud83d\uded1SHOP NOW\ud83d\udc47 \n\ud83d\udecd\ufe0fYou can buy this products, just go to the link in the bio \n\u2705Link in Bio @iamk24__\n\ud83c\udf0eFree shipping worldwide & (Only 24 hours)\n#industry #",
      "url": "https://www.instagram.com/p/C_Fhq8ZxmNm/"
    },
    {
      "shortcode": "C_FhMf3swei",
      "date": "2024-08-25",
      "likes": 1547,
      "comments": 0,
      "is_video": true,
      "video_views": 0,
      "caption": "\ud83d\udecd\ufe0fLINK ORDER IN BIO @iamk24__\n\ud83d\uded1SHOP NOW\ud83d\udc47 \n\ud83d\udecd\ufe0fYou can buy this products, just go to the link in the bio \n\u2705Link in Bio @iamk24__\n\ud83c\udf0eFree shipping worldwide & (Only 24 hours)\n#industry #",
      "url": "https://www.instagram.com/p/C_FhMf3swei/"
    },
    {
      "shortcode": "C96pTFGN3cE",
      "date": "2024-07-27",
      "likes": 10063,
      "comments": 35,
      "is_video": true,
      "video_views": 0,
      "caption": "good idea\ud83d\udca1\n.\n.\n.\n.\n\ud83d\udcfd\ufe0f Video : (unknown) DM for Credit\n\n\ud83d\udc97 Double Tap If You Like This\n\n\ud83d\ude80 Tag Your Friends\n\n\u2764\ufe0f For Us For More Interesting Stuff Like This\n\n\ud83d\udce9 DM for credit or removal",
      "url": "https://www.instagram.com/p/C96pTFGN3cE/"
    },
    {
      "shortcode": "C96pP2fsnRy",
      "date": "2024-07-27",
      "likes": 541,
      "comments": 0,
      "is_video": true,
      "video_views": 0,
      "caption": "good idea\ud83d\udca1\n.\n.\n.\n.\n\ud83d\udcfd\ufe0f Video : (unknown) DM for Credit\n\n\ud83d\udc97 Double Tap If You Like This\n\n\ud83d\ude80 Tag Your Friends\n\n\u2764\ufe0f For Us For More Interesting Stuff Like This\n\n\ud83d\udce9 DM for credit or removal",
      "url": "https://www.instagram.com/p/C96pP2fsnRy/"
    },
    {
      "shortcode": "C9oWvX4CXjk",
      "date": "2024-07-20",
      "likes": 135,
      "comments": 0,
      "is_video": true,
      "video_views": 0,
      "caption": "good idea\ud83d\udca1\n.\n.\n.\n.\n\ud83d\udcfd\ufe0f Video : (unknown) DM for Credit\n\n\ud83d\udc97 Double Tap If You Like This\n\n\ud83d\ude80 Tag Your Friends\n\n\u2764\ufe0f For Us For More Interesting Stuff Like This\n\n\ud83d\udce9 DM for credit or removal",
      "url": "https://www.instagram.com/p/C9oWvX4CXjk/"
    },
    {
      "shortcode": "C82DflrhRyU",
      "date": "2024-06-30",
      "likes": 634,
      "comments": 2,
      "is_video": true,
      "video_views": 0,
      "caption": "\ud83d\udecd\ufe0fLINK ORDER IN BIO @iamk24__\n\ud83d\uded1SHOP NOW\ud83d\udc47 \n\ud83d\udecd\ufe0fYou can buy this products, just go to the link in the bio \n\u2705Link in Bio @iamk24__\n\ud83c\udf0eFree shipping worldwide & (Only 24 hours)\n#industry #",
      "url": "https://www.instagram.com/p/C82DflrhRyU/"
    },
    {
      "shortcode": "C68nPDiJ_OJ",
      "date": "2024-05-14",
      "likes": 2168,
      "comments": 2,
      "is_video": true,
      "video_views": 0,
      "caption": "\ud83d\udc4d\ud83d\udc4d\ud83d\udc4d\n.\n.\n.\n.\n\ud83d\udcfd\ufe0f Video : (unknown) DM for Credit\n\n\ud83d\udc97 Double Tap If You Like This\n\n\ud83d\ude80 Tag Your Friends\n\n\u2764\ufe0f For Us For More Interesting Stuff Like This\n\n\ud83d\udce9 DM for credit or removal reques",
      "url": "https://www.instagram.com/p/C68nPDiJ_OJ/"
    },
    {
      "shortcode": "C68nMvIJxTb",
      "date": "2024-05-14",
      "likes": 10139,
      "comments": 62,
      "is_video": true,
      "video_views": 0,
      "caption": "",
      "url": "https://www.instagram.com/p/C68nMvIJxTb/"
    },
    {
      "shortcode": "C68nJoEppt2",
      "date": "2024-05-14",
      "likes": 10057,
      "comments": 27,
      "is_video": true,
      "video_views": 0,
      "caption": "",
      "url": "https://www.instagram.com/p/C68nJoEppt2/"
    }
  ]
}