{
  "generated_at": "2026-03-15T07:08:16+00:00",
  "date": "2026-03-15",
  "account": "ainterestingaf",
  "profile_url": "https://www.instagram.com/ainterestingaf/",
  "full_name": "AI Gallery",
  "biography": "Welcome to the most interesting AI page on Instagram.\nBrought to you by @sentientagency \ud83e\udd1d",
  "external_url": "https://sentientagency.io/",
  "is_verified": false,
  "followers": 117001,
  "following": 337,
  "posts": 856,
  "recent_post_count": 12,
  "video_post_count": 6,
  "avg_likes": 34275.08,
  "avg_comments": 188.42,
  "avg_video_views": 0.0,
  "avg_video_views_per_video": 0.0,
  "engagement_rate": 29.4557,
  "recent_posts": [
    {
      "shortcode": "DTI76HUkfZj",
      "date": "2026-01-05",
      "likes": 135491,
      "comments": 904,
      "is_video": false,
      "video_views": 0,
      "caption": "Photos of Maduro arriving at the White House\n\nBy Threads/soydiazrodrigo",
      "url": "https://www.instagram.com/p/DTI76HUkfZj/"
    },
    {
      "shortcode": "C7pyG2LubhF",
      "date": "2024-06-01",
      "likes": 137613,
      "comments": 564,
      "is_video": false,
      "video_views": 0,
      "caption": "Mario Kart retro Monaco Grand Prix, feat. Diddy Kong Racing\n\nBy Luke Raynor FB",
      "url": "https://www.instagram.com/p/C7pyG2LubhF/"
    },
    {
      "shortcode": "DV2f6TdDBWA",
      "date": "2026-03-14",
      "likes": 1188,
      "comments": 54,
      "is_video": true,
      "video_views": 0,
      "caption": "Wild \ud83d\ude2d",
      "url": "https://www.instagram.com/p/DV2f6TdDBWA/"
    },
    {
      "shortcode": "DVtzATwGpsl",
      "date": "2026-03-10",
      "likes": 329,
      "comments": 6,
      "is_video": false,
      "video_views": 0,
      "caption": "Fake wedding photos of Tom Holland and Zendaya have gone massively viral on social media, with one Instagram post alone crossing more than 10 million likes \ud83d\ude2c\n\nBy @heroemaniaco",
      "url": "https://www.instagram.com/p/DVtzATwGpsl/"
    },
    {
      "shortcode": "DVji_1UGtv3",
      "date": "2026-03-06",
      "likes": 966,
      "comments": 44,
      "is_video": false,
      "video_views": 0,
      "caption": "The Wolf of the White House \n\nBy @maxdgsov",
      "url": "https://www.instagram.com/p/DVji_1UGtv3/"
    },
    {
      "shortcode": "DVg_j-Cmu5E",
      "date": "2026-03-05",
      "likes": 1029,
      "comments": 20,
      "is_video": false,
      "video_views": 0,
      "caption": "AI imagined a city where thousands of lives are stacked in one building.\nWorking. Eating. Meeting. Living.\n\nWhich floor are you on?\n\nBy @dernadler",
      "url": "https://www.instagram.com/p/DVg_j-Cmu5E/"
    },
    {
      "shortcode": "DVeEAm_EQHS",
      "date": "2026-03-04",
      "likes": 459,
      "comments": 9,
      "is_video": true,
      "video_views": 0,
      "caption": "AI is undefeated \ud83d\ude02",
      "url": "https://www.instagram.com/p/DVeEAm_EQHS/"
    },
    {
      "shortcode": "DVSJS1Rkbzv",
      "date": "2026-02-28",
      "likes": 1252,
      "comments": 34,
      "is_video": false,
      "video_views": 0,
      "caption": "C O L O R W A Y S \n\nBy treads/jslayart",
      "url": "https://www.instagram.com/p/DVSJS1Rkbzv/"
    },
    {
      "shortcode": "DVJu4cwkfvt",
      "date": "2026-02-24",
      "likes": 131771,
      "comments": 603,
      "is_video": true,
      "video_views": 0,
      "caption": "CJ from GTA Goes Pro in Football \u2013 Road to Stardom\n\nBy YT/CanalRedub",
      "url": "https://www.instagram.com/p/DVJu4cwkfvt/"
    },
    {
      "shortcode": "DVFVYVdEUh5",
      "date": "2026-02-23",
      "likes": 332,
      "comments": 6,
      "is_video": true,
      "video_views": 0,
      "caption": "No words...\n\nBy X/EHuanglu",
      "url": "https://www.instagram.com/p/DVFVYVdEUh5/"
    },
    {
      "shortcode": "DU8mxHSjsM5",
      "date": "2026-02-19",
      "likes": 413,
      "comments": 6,
      "is_video": true,
      "video_views": 0,
      "caption": "Naruto (2026) \ud83d\udd25\u2014 Ultimate Ninja Fights | AI Cinematic Trailer\n\nBy X/bluehorizon_ai",
      "url": "https://www.instagram.com/p/DU8mxHSjsM5/"
    },
    {
      "shortcode": "DU4fk4EkYMV",
      "date": "2026-02-18",
      "likes": 458,
      "comments": 11,
      "is_video": true,
      "video_views": 0,
      "caption": "Future of game graphics is INSANE\n\nCompletely photorealistic video games are just a few years away with AI\n\nBy Youtube/Aillusory",
      "url": "https://www.instagram.com/p/DU4fk4EkYMV/"
    }
  ]
}